stream2py/__init__.py
stream2py/buffer_consumer.py
stream2py/buffer_reader.py
stream2py/source_reader.py
stream2py/stream_buffer.py
stream2py/sources/__init__.py
stream2py/sources/audio.py
stream2py/sources/keyboard_input.py
stream2py/sources/net.py
stream2py/sources/pchealth.py
stream2py/sources/plc.py
stream2py/sources/raw_plc.py
stream2py/sources/video.py
stream2py/utility/__init__.py
stream2py/utility/getch.py
stream2py/utility/locked_sorted_deque.py
stream2py/utility/logger.py
stream2py/utility/reader_writer_lock.py
stream2py/utility/sorted_collection.py
stream2py/utility/sorted_deque.py
stream2py/utility/typing_hints.py
stream2py-1.0.6.dist-info/LICENSE
stream2py-1.0.6.dist-info/METADATA
stream2py-1.0.6.dist-info/WHEEL
stream2py-1.0.6.dist-info/top_level.txt
stream2py-1.0.6.dist-info/RECORD
