Metadata-Version: 2.1
Name: stream2py
Version: 1.0.6
Summary: Bring data streams to python with ease
Home-page: https://github.com/i2mint/stream2py
Author: OtoSense
License: mit
Platform: any
